MILAP/BaseModel.py
MILAP/ClassificationModel.py
MILAP/DecisionTreeClassification.py
MILAP/LinearRegressionModel.py
MILAP/LogisticRegressionModel.py
MILAP/RegressionModel.py
MILAP/RidgeRegressionModel.py
MILAP/__init__.py
scikit_milap-0.1.2.dist-info/LICENSE
scikit_milap-0.1.2.dist-info/METADATA
scikit_milap-0.1.2.dist-info/WHEEL
scikit_milap-0.1.2.dist-info/top_level.txt
scikit_milap-0.1.2.dist-info/RECORD
